stv_ascii.py
stv_ascii-0.1.4.dist-info/METADATA
stv_ascii-0.1.4.dist-info/WHEEL
stv_ascii-0.1.4.dist-info/entry_points.txt
stv_ascii-0.1.4.dist-info/top_level.txt
stv_ascii-0.1.4.dist-info/RECORD
