Metadata-Version: 2.4
Name: stv_ascii
Version: 0.1.4
Summary: CLI tool for generating ASCII art from images/videos with GPU acceleration
Home-page: https://github.com/StarWindv/STv_ASCII_ART/
Author: 星灿长风v(StarWindv)
Author-email: starwindv.stv@gmail.com
License: MIT
Classifier: License :: OSI Approved :: MIT License
Classifier: Programming Language :: Python :: 3.10
Classifier: Operating System :: OS Independent
Requires-Dist: tqdm
Requires-Dist: pillow
Requires-Dist: opencv-python
Requires-Dist: numpy
Requires-Dist: torch
Requires-Dist: torchvision
Dynamic: author
Dynamic: author-email
Dynamic: classifier
Dynamic: description
Dynamic: description-content-type
Dynamic: home-page
Dynamic: license
Dynamic: requires-dist
Dynamic: summary
